dash_vite_plugin/__init__.py
dash_vite_plugin/plugin.py
dash_vite_plugin/utils.py
dash_vite_plugin-0.1.3.dist-info/licenses/LICENSE
dash_vite_plugin-0.1.3.dist-info/METADATA
dash_vite_plugin-0.1.3.dist-info/WHEEL
dash_vite_plugin-0.1.3.dist-info/top_level.txt
dash_vite_plugin-0.1.3.dist-info/RECORD
