Metadata-Version: 2.4
Name: dash-vite-plugin
Version: 0.1.3
Summary: A Dash plugin for integrating Vite using Dash 3.x hooks
Author-email: insistence <3055204202@qq.com>
Project-URL: Homepage, https://github.com/HogaStack/dash-vite-plugin
Project-URL: Documentation, https://github.com/HogaStack/dash-vite-plugin
Project-URL: Repository, https://github.com/HogaStack/dash-vite-plugin
Project-URL: Issues, https://github.com/HogaStack/dash-vite-plugin/issues
Classifier: Development Status :: 5 - Production/Stable
Classifier: Intended Audience :: Developers
Classifier: License :: OSI Approved :: MIT License
Classifier: Operating System :: OS Independent
Classifier: Programming Language :: Python :: 3
Classifier: Programming Language :: Python :: 3.8
Classifier: Programming Language :: Python :: 3.9
Classifier: Programming Language :: Python :: 3.10
Classifier: Programming Language :: Python :: 3.11
Classifier: Programming Language :: Python :: 3.12
Classifier: Programming Language :: Python :: 3.13
Classifier: Programming Language :: Python :: 3.14
Classifier: Framework :: Dash
Requires-Python: >=3.8
License-File: LICENSE
Requires-Dist: dash>=3.0.3
Requires-Dist: py-node-manager>=0.1.1
Provides-Extra: dev
Requires-Dist: build; extra == "dev"
Requires-Dist: pytest; extra == "dev"
Requires-Dist: pytest-cov; extra == "dev"
Requires-Dist: twine; extra == "dev"
Dynamic: license-file
